{
    "hive": {
        "class": "",
        "jar": "Location of jar file",  
        "host": "",
        "user": "",
        "pass": ""

    },
    "impala": {
        "class": "",
        "jar": "Location of jar file",
        "host": "",
        "user": "",
        "pass": ""
    },
    "oracle": {
        "dsn": "",
        "user": "",
        "pass": ""
    },
    "postgresql": {
        "host": "",
        "port": 5432,
        "user": "",
        "pass": ""
    },
    "snowflake": {
        "account" : "",
        "user" : "",
        "pass" : "",
        "warehouse" : ""
    },
    "mysql": {
        "host": "",
        "port": 3306,
        "user": "",
        "pass": ""
    }
}